[
  {
    "market": "dabra_night_penal_chart",
    "hits": {
      "open_digit": false,
      "close_digit": false,
      "jodi": true,
      "open_panna": false,
      "close_panna": false
    },
    "predicted": {
      "open_digits": [
        "4",
        "1",
        "0"
      ],
      "close_digits": [
        "8",
        "4",
        "0"
      ],
      "jodis": [
        "48",
        "44",
        "40",
        "18",
        "14",
        "10",
        "08",
        "04",
        "00"
      ],
      "open_pannas": [
        "244",
        "133",
        "225",
        "234",
        "123",
        "144",
        "255",
        "345"
      ],
      "close_pannas": [
        "257",
        "679",
        "578",
        "457",
        "469",
        "189",
        "249",
        "389"
      ]
    },
    "actual": {
      "open_digit": 7,
      "close_digit": 5,
      "jodi": "44",
      "open_panna": "115",
      "close_panna": "112"
    },
    "family_hit": false,
    "line_match": null
  },
  {
    "market": "deluxe_panel_chart",
    "hits": {
      "open_digit": true,
      "close_digit": true,
      "jodi": false,
      "open_panna": false,
      "close_panna": false
    },
    "predicted": {
      "open_digits": [
        "2",
        "6",
        "4"
      ],
      "close_digits": [
        "4",
        "1",
        "8"
      ],
      "jodis": [
        "24",
        "21",
        "28",
        "64",
        "61",
        "68",
        "44",
        "41",
        "48"
      ],
      "open_pannas": [
        "123",
        "133",
        "223",
        "122",
        "233",
        "113",
        "266",
        "135"
      ],
      "close_pannas": [
        "245",
        "345",
        "344",
        "235",
        "145",
        "133",
        "135",
        "233"
      ]
    },
    "actual": {
      "open_digit": 4,
      "close_digit": 4,
      "jodi": "69",
      "open_panna": "112",
      "close_panna": "777"
    },
    "family_hit": false,
    "line_match": null
  },
  {
    "market": "dhan_express_panel_chart",
    "hits": {
      "open_digit": true,
      "close_digit": false,
      "jodi": false,
      "open_panna": false,
      "close_panna": false
    },
    "predicted": {
      "open_digits": [
        "6",
        "8",
        "1"
      ],
      "close_digits": [
        "7",
        "5",
        "0"
      ],
      "jodis": [
        "67",
        "65",
        "60",
        "87",
        "85",
        "80",
        "17",
        "15",
        "10"
      ],
      "open_pannas": [
        "136",
        "126",
        "137",
        "135",
        "456",
        "367",
        "346",
        "256"
      ],
      "close_pannas": [
        "158",
        "167",
        "478",
        "188",
        "146",
        "127",
        "248",
        "126"
      ]
    },
    "actual": {
      "open_digit": 6,
      "close_digit": 6,
      "jodi": "02",
      "open_panna": "112",
      "close_panna": "110"
    },
    "family_hit": false,
    "line_match": null
  },
  {
    "market": "kalyan_morning_penal_chart",
    "hits": {
      "open_digit": true,
      "close_digit": false,
      "jodi": false,
      "open_panna": false,
      "close_panna": false
    },
    "predicted": {
      "open_digits": [
        "2",
        "6",
        "3"
      ],
      "close_digits": [
        "7",
        "1",
        "9"
      ],
      "jodis": [
        "27",
        "21",
        "29",
        "67",
        "61",
        "69",
        "37",
        "31",
        "39"
      ],
      "open_pannas": [
        "455",
        "236",
        "247",
        "367",
        "147",
        "246",
        "156",
        "467"
      ],
      "close_pannas": [
        "467",
        "457",
        "267",
        "128",
        "166",
        "348",
        "346",
        "568"
      ]
    },
    "actual": {
      "open_digit": 6,
      "close_digit": 2,
      "jodi": "32",
      "open_panna": "777",
      "close_panna": "115"
    },
    "family_hit": false,
    "line_match": null
  },
  {
    "market": "kalyan_penal_chart",
    "hits": {
      "open_digit": false,
      "close_digit": true,
      "jodi": false,
      "open_panna": false,
      "close_panna": false
    },
    "predicted": {
      "open_digits": [
        "9",
        "3",
        "6"
      ],
      "close_digits": [
        "7",
        "0",
        "4"
      ],
      "jodis": [
        "97",
        "90",
        "94",
        "37",
        "30",
        "34",
        "67",
        "60",
        "64"
      ],
      "open_pannas": [
        "478",
        "599",
        "349",
        "490",
        "480",
        "270",
        "890",
        "680"
      ],
      "close_pannas": [
        "188",
        "248",
        "368",
        "137",
        "147",
        "246",
        "278",
        "256"
      ]
    },
    "actual": {
      "open_digit": 2,
      "close_digit": 4,
      "jodi": "57",
      "open_panna": "112",
      "close_panna": "115"
    },
    "family_hit": false,
    "line_match": null
  },
  {
    "market": "karnataka_day_panel_chart",
    "hits": {
      "open_digit": false,
      "close_digit": true,
      "jodi": false,
      "open_panna": false,
      "close_panna": false
    },
    "predicted": {
      "open_digits": [
        "8",
        "6",
        "2"
      ],
      "close_digits": [
        "9",
        "7",
        "4"
      ],
      "jodis": [
        "89",
        "87",
        "84",
        "69",
        "67",
        "64",
        "29",
        "27",
        "24"
      ],
      "open_pannas": [
        "169",
        "459",
        "899",
        "578",
        "577",
        "568",
        "128",
        "399"
      ],
      "close_pannas": [
        "478",
        "278",
        "590",
        "589",
        "790",
        "678",
        "480",
        "280"
      ]
    },
    "actual": {
      "open_digit": 3,
      "close_digit": 4,
      "jodi": "94",
      "open_panna": "777",
      "close_panna": "116"
    },
    "family_hit": false,
    "line_match": null
  },
  {
    "market": "karnataka_night_panel_chart",
    "hits": {
      "open_digit": false,
      "close_digit": false,
      "jodi": false,
      "open_panna": true,
      "close_panna": true
    },
    "predicted": {
      "open_digits": [
        "3",
        "4",
        "7"
      ],
      "close_digits": [
        "3",
        "0",
        "2"
      ],
      "jodis": [
        "33",
        "30",
        "32",
        "43",
        "40",
        "42",
        "73",
        "70",
        "72"
      ],
      "open_pannas": [
        "123",
        "124",
        "224",
        "334",
        "112",
        "234",
        "113",
        "344"
      ],
      "close_pannas": [
        "133",
        "123",
        "122",
        "124",
        "113",
        "224",
        "234",
        "112"
      ]
    },
    "actual": {
      "open_digit": 5,
      "close_digit": 4,
      "jodi": "54",
      "open_panna": "112",
      "close_panna": "113"
    },
    "family_hit": false,
    "line_match": null
  },
  {
    "market": "kbc_bombay_penal_chart",
    "hits": {
      "open_digit": true,
      "close_digit": false,
      "jodi": false,
      "open_panna": false,
      "close_panna": false
    },
    "predicted": {
      "open_digits": [
        "8",
        "7",
        "4"
      ],
      "close_digits": [
        "4",
        "2",
        "1"
      ],
      "jodis": [
        "84",
        "82",
        "81",
        "74",
        "72",
        "71",
        "44",
        "42",
        "41"
      ],
      "open_pannas": [
        "279",
        "368",
        "257",
        "789",
        "119",
        "229",
        "367",
        "269"
      ],
      "close_pannas": [
        "234",
        "455",
        "113",
        "115",
        "145",
        "235",
        "333",
        "245"
      ]
    },
    "actual": {
      "open_digit": 4,
      "close_digit": 6,
      "jodi": "46",
      "open_panna": "777",
      "close_panna": "110"
    },
    "family_hit": false,
    "line_match": null
  },
  {
    "market": "madhur_day_panel_chart",
    "hits": {
      "open_digit": false,
      "close_digit": true,
      "jodi": false,
      "open_panna": false,
      "close_panna": false
    },
    "predicted": {
      "open_digits": [
        "4",
        "6",
        "0"
      ],
      "close_digits": [
        "0",
        "1",
        "8"
      ],
      "jodis": [
        "40",
        "41",
        "48",
        "60",
        "61",
        "68",
        "00",
        "01",
        "08"
      ],
      "open_pannas": [
        "455",
        "345",
        "245",
        "233",
        "135",
        "124",
        "134",
        "333"
      ],
      "close_pannas": [
        "669",
        "190",
        "689",
        "580",
        "569",
        "130",
        "360",
        "300"
      ]
    },
    "actual": {
      "open_digit": 5,
      "close_digit": 1,
      "jodi": "59",
      "open_panna": "777",
      "close_panna": "100"
    },
    "family_hit": false,
    "line_match": null
  },
  {
    "market": "main_bazar_panel_chart",
    "hits": {
      "open_digit": false,
      "close_digit": true,
      "jodi": false,
      "open_panna": true,
      "close_panna": false
    },
    "predicted": {
      "open_digits": [
        "3",
        "7",
        "2"
      ],
      "close_digits": [
        "4",
        "9",
        "7"
      ],
      "jodis": [
        "34",
        "39",
        "37",
        "74",
        "79",
        "77",
        "24",
        "29",
        "27"
      ],
      "open_pannas": [
        "223",
        "133",
        "344",
        "234",
        "233",
        "124",
        "112",
        "134"
      ],
      "close_pannas": [
        "135",
        "255",
        "244",
        "115",
        "224",
        "345",
        "123",
        "235"
      ]
    },
    "actual": {
      "open_digit": 0,
      "close_digit": 9,
      "jodi": "07",
      "open_panna": "112",
      "close_panna": "289"
    },
    "family_hit": false,
    "line_match": null
  },
  {
    "market": "main_bombay_panel_chart",
    "hits": {
      "open_digit": false,
      "close_digit": false,
      "jodi": false,
      "open_panna": true,
      "close_panna": false
    },
    "predicted": {
      "open_digits": [
        "3",
        "1",
        "7"
      ],
      "close_digits": [
        "8",
        "6",
        "4"
      ],
      "jodis": [
        "38",
        "36",
        "34",
        "18",
        "16",
        "14",
        "78",
        "76",
        "74"
      ],
      "open_pannas": [
        "224",
        "124",
        "122",
        "144",
        "133",
        "113",
        "112",
        "344"
      ],
      "close_pannas": [
        "357",
        "679",
        "799",
        "138",
        "358",
        "127",
        "678",
        "158"
      ]
    },
    "actual": {
      "open_digit": 5,
      "close_digit": 0,
      "jodi": "50",
      "open_panna": "112",
      "close_panna": "110"
    },
    "family_hit": false,
    "line_match": null
  },
  {
    "market": "main_ratan_penal_chart",
    "hits": {
      "open_digit": false,
      "close_digit": true,
      "jodi": false,
      "open_panna": true,
      "close_panna": false
    },
    "predicted": {
      "open_digits": [
        "3",
        "7",
        "2"
      ],
      "close_digits": [
        "4",
        "9",
        "7"
      ],
      "jodis": [
        "34",
        "39",
        "37",
        "74",
        "79",
        "77",
        "24",
        "29",
        "27"
      ],
      "open_pannas": [
        "223",
        "133",
        "344",
        "234",
        "233",
        "124",
        "112",
        "134"
      ],
      "close_pannas": [
        "135",
        "255",
        "244",
        "115",
        "224",
        "345",
        "123",
        "235"
      ]
    },
    "actual": {
      "open_digit": 0,
      "close_digit": 9,
      "jodi": "35",
      "open_panna": "112",
      "close_panna": "289"
    },
    "family_hit": false,
    "line_match": null
  },
  {
    "market": "milan_night_penal_chart",
    "hits": {
      "open_digit": true,
      "close_digit": false,
      "jodi": false,
      "open_panna": false,
      "close_panna": false
    },
    "predicted": {
      "open_digits": [
        "0",
        "3",
        "2"
      ],
      "close_digits": [
        "8",
        "0",
        "9"
      ],
      "jodis": [
        "08",
        "00",
        "09",
        "38",
        "30",
        "39",
        "28",
        "20",
        "29"
      ],
      "open_pannas": [
        "689",
        "259",
        "600",
        "159",
        "790",
        "570",
        "299",
        "189"
      ],
      "close_pannas": [
        "379",
        "138",
        "399",
        "277",
        "189",
        "689",
        "127",
        "578"
      ]
    },
    "actual": {
      "open_digit": 2,
      "close_digit": 2,
      "jodi": "25",
      "open_panna": "888",
      "close_panna": "113"
    },
    "family_hit": false,
    "line_match": null
  },
  {
    "market": "morning_syndicate_penal_chart",
    "hits": {
      "open_digit": true,
      "close_digit": false,
      "jodi": false,
      "open_panna": false,
      "close_panna": false
    },
    "predicted": {
      "open_digits": [
        "7",
        "6",
        "3"
      ],
      "close_digits": [
        "2",
        "8",
        "3"
      ],
      "jodis": [
        "72",
        "78",
        "73",
        "62",
        "68",
        "63",
        "32",
        "38",
        "33"
      ],
      "open_pannas": [
        "338",
        "246",
        "458",
        "678",
        "158",
        "167",
        "388",
        "256"
      ],
      "close_pannas": [
        "112",
        "233",
        "122",
        "123",
        "113",
        "133",
        "223",
        "237"
      ]
    },
    "actual": {
      "open_digit": 7,
      "close_digit": 6,
      "jodi": "76",
      "open_panna": "112",
      "close_panna": "777"
    },
    "family_hit": false,
    "line_match": null
  },
  {
    "market": "prabhat_night_panel_chart",
    "hits": {
      "open_digit": false,
      "close_digit": true,
      "jodi": true,
      "open_panna": false,
      "close_panna": false
    },
    "predicted": {
      "open_digits": [
        "1",
        "5",
        "8"
      ],
      "close_digits": [
        "3",
        "7",
        "1"
      ],
      "jodis": [
        "13",
        "17",
        "11",
        "53",
        "57",
        "51",
        "83",
        "87",
        "81"
      ],
      "open_pannas": [
        "350",
        "790",
        "120",
        "470",
        "130",
        "230",
        "260",
        "340"
      ],
      "close_pannas": [
        "124",
        "112",
        "134",
        "244",
        "144",
        "123",
        "122",
        "234"
      ]
    },
    "actual": {
      "open_digit": 3,
      "close_digit": 7,
      "jodi": "57",
      "open_panna": "113",
      "close_panna": "100"
    },
    "family_hit": false,
    "line_match": null
  },
  {
    "market": "raja_rani_morning_panel_chart",
    "hits": {
      "open_digit": true,
      "close_digit": true,
      "jodi": true,
      "open_panna": false,
      "close_panna": false
    },
    "predicted": {
      "open_digits": [
        "0",
        "3",
        "4"
      ],
      "close_digits": [
        "1",
        "4",
        "5"
      ],
      "jodis": [
        "01",
        "04",
        "05",
        "31",
        "34",
        "35",
        "41",
        "44",
        "45"
      ],
      "open_pannas": [
        "779",
        "680",
        "159",
        "490",
        "670",
        "350",
        "400",
        "359"
      ],
      "close_pannas": [
        "290",
        "780",
        "380",
        "100",
        "200",
        "160",
        "370",
        "150"
      ]
    },
    "actual": {
      "open_digit": 3,
      "close_digit": 1,
      "jodi": "34",
      "open_panna": "100",
      "close_panna": "112"
    },
    "family_hit": false,
    "line_match": null
  },
  {
    "market": "rajdhani_day_penal_chart",
    "hits": {
      "open_digit": true,
      "close_digit": false,
      "jodi": false,
      "open_panna": false,
      "close_panna": false
    },
    "predicted": {
      "open_digits": [
        "2",
        "6",
        "7"
      ],
      "close_digits": [
        "4",
        "8",
        "0"
      ],
      "jodis": [
        "24",
        "28",
        "20",
        "64",
        "68",
        "60",
        "74",
        "78",
        "70"
      ],
      "open_pannas": [
        "223",
        "123",
        "133",
        "113",
        "112",
        "233",
        "122",
        "177"
      ],
      "close_pannas": [
        "115",
        "235",
        "123",
        "125",
        "124",
        "334",
        "224",
        "134"
      ]
    },
    "actual": {
      "open_digit": 6,
      "close_digit": 3,
      "jodi": "65",
      "open_panna": "777",
      "close_panna": "110"
    },
    "family_hit": false,
    "line_match": null
  },
  {
    "market": "rajdhani_night_penal_chart",
    "hits": {
      "open_digit": true,
      "close_digit": true,
      "jodi": false,
      "open_panna": false,
      "close_panna": false
    },
    "predicted": {
      "open_digits": [
        "2",
        "8",
        "3"
      ],
      "close_digits": [
        "7",
        "6",
        "2"
      ],
      "jodis": [
        "27",
        "26",
        "22",
        "87",
        "86",
        "82",
        "37",
        "36",
        "32"
      ],
      "open_pannas": [
        "233",
        "122",
        "113",
        "123",
        "133",
        "112",
        "223",
        "237"
      ],
      "close_pannas": [
        "557",
        "138",
        "147",
        "177",
        "377",
        "488",
        "678",
        "256"
      ]
    },
    "actual": {
      "open_digit": 3,
      "close_digit": 2,
      "jodi": "31",
      "open_panna": "110",
      "close_panna": "100"
    },
    "family_hit": false,
    "line_match": null
  },
  {
    "market": "rithi_sridevi_panel_chart",
    "hits": {
      "open_digit": true,
      "close_digit": true,
      "jodi": true,
      "open_panna": false,
      "close_panna": false
    },
    "predicted": {
      "open_digits": [
        "8",
        "3",
        "9"
      ],
      "close_digits": [
        "2",
        "5",
        "9"
      ],
      "jodis": [
        "82",
        "85",
        "89",
        "32",
        "35",
        "39",
        "92",
        "95",
        "99"
      ],
      "open_pannas": [
        "779",
        "238",
        "489",
        "159",
        "137",
        "388",
        "467",
        "347"
      ],
      "close_pannas": [
        "122",
        "222",
        "123",
        "145",
        "556",
        "466",
        "266",
        "446"
      ]
    },
    "actual": {
      "open_digit": 9,
      "close_digit": 5,
      "jodi": "35",
      "open_panna": "116",
      "close_panna": "113"
    },
    "family_hit": false,
    "line_match": null
  },
  {
    "market": "sivaji_panel_chart",
    "hits": {
      "open_digit": false,
      "close_digit": false,
      "jodi": false,
      "open_panna": false,
      "close_panna": true
    },
    "predicted": {
      "open_digits": [
        "5",
        "7",
        "2"
      ],
      "close_digits": [
        "8",
        "1",
        "3"
      ],
      "jodis": [
        "58",
        "51",
        "53",
        "78",
        "71",
        "73",
        "28",
        "21",
        "23"
      ],
      "open_pannas": [
        "256",
        "134",
        "146",
        "456",
        "246",
        "136",
        "245",
        "166"
      ],
      "close_pannas": [
        "119",
        "139",
        "149",
        "258",
        "229",
        "148",
        "559",
        "357"
      ]
    },
    "actual": {
      "open_digit": 8,
      "close_digit": 2,
      "jodi": "09",
      "open_panna": "112",
      "close_panna": "149"
    },
    "family_hit": false,
    "line_match": null
  },
  {
    "market": "sridevi_morning_panel_chart",
    "hits": {
      "open_digit": false,
      "close_digit": false,
      "jodi": false,
      "open_panna": false,
      "close_panna": true
    },
    "predicted": {
      "open_digits": [
        "1",
        "5",
        "4"
      ],
      "close_digits": [
        "1",
        "9",
        "2"
      ],
      "jodis": [
        "11",
        "19",
        "12",
        "51",
        "59",
        "52",
        "41",
        "49",
        "42"
      ],
      "open_pannas": [
        "140",
        "260",
        "180",
        "900",
        "120",
        "150",
        "390",
        "250"
      ],
      "close_pannas": [
        "100",
        "360",
        "180",
        "110",
        "160",
        "500",
        "300",
        "800"
      ]
    },
    "actual": {
      "open_digit": 7,
      "close_digit": 3,
      "jodi": "73",
      "open_panna": "888",
      "close_panna": "160"
    },
    "family_hit": false,
    "line_match": null
  },
  {
    "market": "sridevi_satta_penal_chart",
    "hits": {
      "open_digit": false,
      "close_digit": true,
      "jodi": false,
      "open_panna": false,
      "close_panna": false
    },
    "predicted": {
      "open_digits": [
        "4",
        "3",
        "0"
      ],
      "close_digits": [
        "0",
        "7",
        "8"
      ],
      "jodis": [
        "40",
        "47",
        "48",
        "30",
        "37",
        "38",
        "00",
        "07",
        "08"
      ],
      "open_pannas": [
        "145",
        "245",
        "125",
        "445",
        "224",
        "345",
        "234",
        "233"
      ],
      "close_pannas": [
        "370",
        "449",
        "880",
        "599",
        "789",
        "570",
        "489",
        "360"
      ]
    },
    "actual": {
      "open_digit": 1,
      "close_digit": 7,
      "jodi": "71",
      "open_panna": "100",
      "close_panna": "100"
    },
    "family_hit": false,
    "line_match": null
  },
  {
    "market": "supreme_day_panel_chart",
    "hits": {
      "open_digit": true,
      "close_digit": true,
      "jodi": false,
      "open_panna": false,
      "close_panna": false
    },
    "predicted": {
      "open_digits": [
        "4",
        "5",
        "0"
      ],
      "close_digits": [
        "8",
        "4",
        "6"
      ],
      "jodis": [
        "48",
        "44",
        "46",
        "58",
        "54",
        "56",
        "08",
        "04",
        "06"
      ],
      "open_pannas": [
        "133",
        "234",
        "135",
        "334",
        "455",
        "134",
        "124",
        "224"
      ],
      "close_pannas": [
        "459",
        "467",
        "669",
        "458",
        "148",
        "248",
        "169",
        "469"
      ]
    },
    "actual": {
      "open_digit": 5,
      "close_digit": 8,
      "jodi": "79",
      "open_panna": "112",
      "close_panna": "477"
    },
    "family_hit": false,
    "line_match": null
  },
  {
    "market": "syndicate_night_penal_chart",
    "hits": {
      "open_digit": false,
      "close_digit": true,
      "jodi": false,
      "open_panna": false,
      "close_panna": false
    },
    "predicted": {
      "open_digits": [
        "1",
        "9",
        "2"
      ],
      "close_digits": [
        "8",
        "7",
        "3"
      ],
      "jodis": [
        "18",
        "17",
        "13",
        "98",
        "97",
        "93",
        "28",
        "27",
        "23"
      ],
      "open_pannas": [
        "380",
        "360",
        "330",
        "600",
        "470",
        "790",
        "670",
        "200"
      ],
      "close_pannas": [
        "459",
        "359",
        "457",
        "288",
        "277",
        "489",
        "239",
        "478"
      ]
    },
    "actual": {
      "open_digit": 4,
      "close_digit": 3,
      "jodi": "29",
      "open_panna": "777",
      "close_panna": "777"
    },
    "family_hit": false,
    "line_match": null
  }
]